amalgama/__init__.py
amalgama/amalgama.py
amalgama-0.2.3.dist-info/LICENSE
amalgama-0.2.3.dist-info/WHEEL
amalgama-0.2.3.dist-info/METADATA
amalgama-0.2.3.dist-info/RECORD
