Metadata-Version: 2.1
Name: amalgama
Version: 0.2.3
Summary: amalgama scraper
License: MIT
Author: Andriy Orehov
Author-email: andriyorehov@gmail.com
Requires-Python: >=3.5,<4.0
Classifier: License :: OSI Approved :: MIT License
Classifier: Programming Language :: Python :: 3
Classifier: Programming Language :: Python :: 3.5
Classifier: Programming Language :: Python :: 3.6
Classifier: Programming Language :: Python :: 3.7
Classifier: Programming Language :: Python :: 3.8
Requires-Dist: pyquery (>=1.4,<2.0)
Requires-Dist: python-slugify (>=2.0,<3.0)
Requires-Dist: unidecode (>=1.0,<2.0)
Project-URL: Bug Tracker, https://github.com/andriyor/amalgama-pq/issues
Project-URL: Code, https://github.com/andriyor/amalgama-pq
Project-URL: CI, https://travis-ci.org/Live-Lyrics/amalgama-pq
